combstruct2json.cpython-36m-darwin.so
combstruct2json-0.95.dist-info/METADATA
combstruct2json-0.95.dist-info/RECORD
combstruct2json-0.95.dist-info/WHEEL
combstruct2json-0.95.dist-info/top_level.txt
